data/ass1.txt
data/ass2.txt
data/ass3.txt
data/ass4.txt
data/ass5.txt
data/ass6.txt
data/ass7.txt
file/__init__.py
file/file2.py
jadugar-1.9.dist-info/METADATA
jadugar-1.9.dist-info/WHEEL
jadugar-1.9.dist-info/top_level.txt
jadugar-1.9.dist-info/RECORD
