Metadata-Version: 2.1
Name: jadugar
Version: 1.9
Summary: Jadugar is a fun project for experimentation with Python packages, read more at project links below
Author: random
Project-URL: Documentation, https://pypi.org/project/jadugar/
